{
   "max_mmode_perf_event" : "50",
   "memmap" : {
      "cosnoleio" : "0xd0580000"
   },
   "reset_vec" : "0x80000000",
   "triggers" : [
      {
         "poke_mask" : [
            "0x081818c7",
            "0xffffffff",
            "0x00000000"
         ],
         "reset" : [
            "0x23e00000",
            "0x00000000",
            "0x00000000"
         ],
         "mask" : [
            "0x081818c7",
            "0xffffffff",
            "0x00000000"
         ]
      },
      {
         "mask" : [
            "0x081818c7",
            "0xffffffff",
            "0x00000000"
         ],
         "reset" : [
            "0x23e00000",
            "0x00000000",
            "0x00000000"
         ],
         "poke_mask" : [
            "0x081818c7",
            "0xffffffff",
            "0x00000000"
         ]
      },
      {
         "reset" : [
            "0x23e00000",
            "0x00000000",
            "0x00000000"
         ],
         "poke_mask" : [
            "0x081818c7",
            "0xffffffff",
            "0x00000000"
         ],
         "mask" : [
            "0x081818c7",
            "0xffffffff",
            "0x00000000"
         ]
      },
      {
         "reset" : [
            "0x23e00000",
            "0x00000000",
            "0x00000000"
         ],
         "poke_mask" : [
            "0x081818c7",
            "0xffffffff",
            "0x00000000"
         ],
         "mask" : [
            "0x081818c7",
            "0xffffffff",
            "0x00000000"
         ]
      }
   ],
   "dccm" : {
      "size" : "0x10000",
      "region" : "0xf",
      "offset" : "0x40000"
   },
   "load_error_rollback" : "1",
   "even_odd_trigger_chains" : "true",
   "harts" : 1,
   "nmi_vec" : "0x11110000",
   "csr" : {
      "pmpaddr4" : {
         "exists" : "false"
      },
      "mstatus" : {
         "mask" : "0x88",
         "exists" : "true",
         "reset" : "0x1800"
      },
      "meicurpl" : {
         "exists" : "true",
         "mask" : "0xf",
         "number" : "0xbcc",
         "reset" : "0x0",
         "comment" : "External interrupt current priority level."
      },
      "mhpmcounter5h" : {
         "exists" : "true",
         "mask" : "0xffffffff",
         "reset" : "0x0"
      },
      "mhpmevent6" : {
         "mask" : "0xffffffff",
         "exists" : "true",
         "reset" : "0x0"
      },
      "pmpaddr6" : {
         "exists" : "false"
      },
      "meipt" : {
         "comment" : "External interrupt priority threshold.",
         "reset" : "0x0",
         "number" : "0xbc9",
         "mask" : "0xf",
         "exists" : "true"
      },
      "pmpaddr1" : {
         "exists" : "false"
      },
      "mhpmcounter4h" : {
         "reset" : "0x0",
         "mask" : "0xffffffff",
         "exists" : "true"
      },
      "mfdc" : {
         "number" : "0x7f9",
         "reset" : "0x00070000",
         "exists" : "true",
         "mask" : "0x000707ff"
      },
      "pmpaddr9" : {
         "exists" : "false"
      },
      "dicago" : {
         "exists" : "true",
         "debug" : "true",
         "mask" : "0x0",
         "number" : "0x7cb",
         "comment" : "Cache diagnostics.",
         "reset" : "0x0"
      },
      "pmpaddr13" : {
         "exists" : "false"
      },
      "pmpcfg2" : {
         "exists" : "false"
      },
      "mhpmcounter6h" : {
         "exists" : "true",
         "mask" : "0xffffffff",
         "reset" : "0x0"
      },
      "dmst" : {
         "exists" : "true",
         "debug" : "true",
         "mask" : "0x0",
         "number" : "0x7c4",
         "comment" : "Memory synch trigger: Flush caches in debug mode.",
         "reset" : "0x0"
      },
      "misa" : {
         "reset" : "0x40001104",
         "exists" : "true",
         "mask" : "0x0"
      },
      "miccmect" : {
         "exists" : "true",
         "mask" : "0xffffffff",
         "number" : "0x7f1",
         "reset" : "0x0"
      },
      "mhpmevent3" : {
         "exists" : "true",
         "mask" : "0xffffffff",
         "reset" : "0x0"
      },
      "pmpaddr8" : {
         "exists" : "false"
      },
      "meicidpl" : {
         "number" : "0xbcb",
         "comment" : "External interrupt claim id priority level.",
         "reset" : "0x0",
         "exists" : "true",
         "mask" : "0xf"
      },
      "pmpaddr7" : {
         "exists" : "false"
      },
      "pmpaddr12" : {
         "exists" : "false"
      },
      "mimpid" : {
         "exists" : "true",
         "mask" : "0x0",
         "reset" : "0x1"
      },
      "mhpmcounter4" : {
         "reset" : "0x0",
         "mask" : "0xffffffff",
         "exists" : "true"
      },
      "pmpcfg1" : {
         "exists" : "false"
      },
      "pmpcfg3" : {
         "exists" : "false"
      },
      "mip" : {
         "reset" : "0x0",
         "poke_mask" : "0x40000888",
         "exists" : "true",
         "mask" : "0x0"
      },
      "micect" : {
         "reset" : "0x0",
         "number" : "0x7f0",
         "mask" : "0xffffffff",
         "exists" : "true"
      },
      "dcsr" : {
         "exists" : "true",
         "mask" : "0x00008c04",
         "reset" : "0x40000003",
         "poke_mask" : "0x00008dcc"
      },
      "marchid" : {
         "reset" : "0x0000000b",
         "mask" : "0x0",
         "exists" : "true"
      },
      "meicpct" : {
         "mask" : "0x0",
         "exists" : "true",
         "reset" : "0x0",
         "comment" : "External claim id/priority capture.",
         "number" : "0xbca"
      },
      "cycle" : {
         "exists" : "false"
      },
      "mhpmevent5" : {
         "reset" : "0x0",
         "exists" : "true",
         "mask" : "0xffffffff"
      },
      "mie" : {
         "reset" : "0x0",
         "mask" : "0x40000888",
         "exists" : "true"
      },
      "instret" : {
         "exists" : "false"
      },
      "mcpc" : {
         "exists" : "true",
         "mask" : "0x0",
         "number" : "0x7c2",
         "reset" : "0x0"
      },
      "mhpmcounter3" : {
         "reset" : "0x0",
         "mask" : "0xffffffff",
         "exists" : "true"
      },
      "dicawics" : {
         "debug" : "true",
         "exists" : "true",
         "mask" : "0x0130fffc",
         "number" : "0x7c8",
         "comment" : "Cache diagnostics.",
         "reset" : "0x0"
      },
      "mpmc" : {
         "exists" : "true",
         "mask" : "0x0",
         "number" : "0x7c6",
         "reset" : "0x0",
         "comment" : "Core pause: Implemented as read only."
      },
      "mdccmect" : {
         "exists" : "true",
         "mask" : "0xffffffff",
         "number" : "0x7f2",
         "reset" : "0x0"
      },
      "pmpaddr10" : {
         "exists" : "false"
      },
      "mcgc" : {
         "mask" : "0x000001ff",
         "exists" : "true",
         "reset" : "0x0",
         "poke_mask" : "0x000001ff",
         "number" : "0x7f8"
      },
      "pmpaddr2" : {
         "exists" : "false"
      },
      "tselect" : {
         "mask" : "0x3",
         "exists" : "true",
         "reset" : "0x0"
      },
      "mhpmcounter5" : {
         "mask" : "0xffffffff",
         "exists" : "true",
         "reset" : "0x0"
      },
      "dicad1" : {
         "mask" : "0x3",
         "exists" : "true",
         "debug" : "true",
         "comment" : "Cache diagnostics.",
         "reset" : "0x0",
         "number" : "0x7ca"
      },
      "pmpaddr14" : {
         "exists" : "false"
      },
      "pmpaddr11" : {
         "exists" : "false"
      },
      "time" : {
         "exists" : "false"
      },
      "mvendorid" : {
         "reset" : "0x45",
         "mask" : "0x0",
         "exists" : "true"
      },
      "pmpaddr3" : {
         "exists" : "false"
      },
      "pmpaddr5" : {
         "exists" : "false"
      },
      "mhpmevent4" : {
         "reset" : "0x0",
         "exists" : "true",
         "mask" : "0xffffffff"
      },
      "mhpmcounter6" : {
         "reset" : "0x0",
         "exists" : "true",
         "mask" : "0xffffffff"
      },
      "pmpaddr15" : {
         "exists" : "false"
      },
      "dicad0" : {
         "number" : "0x7c9",
         "reset" : "0x0",
         "comment" : "Cache diagnostics.",
         "debug" : "true",
         "exists" : "true",
         "mask" : "0xffffffff"
      },
      "pmpaddr0" : {
         "exists" : "false"
      },
      "pmpcfg0" : {
         "exists" : "false"
      },
      "mhpmcounter3h" : {
         "reset" : "0x0",
         "mask" : "0xffffffff",
         "exists" : "true"
      }
   },
   "num_mmode_perf_regs" : "4",
   "pic" : {
      "total_int_plus1" : 9,
      "offset" : "0xc0000",
      "meie_offset" : "0x2000",
      "size" : "0x8000",
      "bits" : 15,
      "total_int" : 8,
      "mpiccfg_offset" : "0x3000",
      "meipl_offset" : "0x0000",
      "meip_offset" : "0x1000",
      "region" : "0xf",
      "meigwctrl_offset" : "0x4000",
      "meipt_offset" : "0x3004",
      "meigwclr_offset" : "0x5000",
      "int_words" : 1
   },
   "store_error_rollback" : "0",
   "xlen" : 32
}
